devicetype/__init__.py
devicetype/browser.py
devicetype/conf.py
devicetype/context_processors.py
devicetype/middleware.py
devicetype/models.py
django_devicetype_templates-0.2.3.dist-info/DESCRIPTION.rst
django_devicetype_templates-0.2.3.dist-info/METADATA
django_devicetype_templates-0.2.3.dist-info/RECORD
django_devicetype_templates-0.2.3.dist-info/WHEEL
django_devicetype_templates-0.2.3.dist-info/metadata.json
django_devicetype_templates-0.2.3.dist-info/top_level.txt
