Metadata-Version: 2.0
Name: django-devicetype-templates
Version: 0.2.3
Summary: Django library to serve different templates for different device types
Home-page: https://github.com/whit/django-devicetype-templates
Author: Vitek Pliska
Author-email: whit@jizak.cz
License: BSD
Platform: UNKNOWN
Classifier: Development Status :: 4 - Beta
Classifier: Intended Audience :: Developers
Classifier: License :: OSI Approved :: BSD License
Classifier: Operating System :: OS Independent
Classifier: Framework :: Django
Classifier: Programming Language :: Python :: 2.7
Classifier: Programming Language :: Python :: 3.3
Classifier: Programming Language :: Python :: 3.4
Classifier: Programming Language :: Python :: 3.5
Classifier: Topic :: Internet :: WWW/HTTP :: Dynamic Content
Classifier: Topic :: Software Development :: Libraries :: Python Modules
Requires-Dist: Django (<1.12,>=1.7)
